pymcaspec/__init__.py
pymcaspec/pymcaspec.py
pymcaspec/utils.py
pymcaspec-0.1.dist-info/METADATA
pymcaspec-0.1.dist-info/WHEEL
pymcaspec-0.1.dist-info/top_level.txt
pymcaspec-0.1.dist-info/RECORD
