Metadata-Version: 2.1
Name: pymcaspec
Version: 0.1
Summary: Parser for spec file
Home-page: http://github.com/mpmdean/pymcaspec
Author: Mark Dean
Author-email: mdean@bnl.gov
License: MIT
Platform: UNKNOWN
Requires: numpy
Requires: matplotlib
Requires: PyMca5
